jupyterannotate/__init__.py
jupyterannotate/_frontend.py
jupyterannotate/_version.py
jupyterannotate/annotate.py
jupyterannotate/labextension/build_log.json
jupyterannotate/labextension/package.json
jupyterannotate/labextension/static/lib_index_js.9a0214f7bdb2b187ec6b.js
jupyterannotate/labextension/static/lib_index_js.9a0214f7bdb2b187ec6b.js.map
jupyterannotate/labextension/static/lib_plugin_js.439d59b8a5ba54d0b3dd.js
jupyterannotate/labextension/static/lib_plugin_js.439d59b8a5ba54d0b3dd.js.map
jupyterannotate/labextension/static/lib_widget_js.a78957a21bc22a60aad1.js
jupyterannotate/labextension/static/lib_widget_js.a78957a21bc22a60aad1.js.map
jupyterannotate/labextension/static/remoteEntry.9aa45be424c88199928a.js
jupyterannotate/labextension/static/remoteEntry.9aa45be424c88199928a.js.map
jupyterannotate/labextension/static/style.js
jupyterannotate/labextension/static/vendors-node_modules_css-loader_dist_runtime_api_js-node_modules_preact_hooks_dist_hooks_modu-fd345c.844a5ab97fdbab5d6715.js
jupyterannotate/labextension/static/vendors-node_modules_css-loader_dist_runtime_api_js-node_modules_preact_hooks_dist_hooks_modu-fd345c.844a5ab97fdbab5d6715.js.map
jupyterannotate/nbextension/extension.js
jupyterannotate/nbextension/index.js
jupyterannotate/nbextension/index.js.map
jupyterannotate/tests/__init__.py
jupyterannotate/tests/conftest.py
jupyterannotate/tests/test_annotate.py
jupyterannotate/tests/test_nbextension_path.py
jupyterannotate-0.1.3.data/data/etc/jupyter/nbconfig/notebook.d/jupyterannotate.json
jupyterannotate-0.1.3.data/data/share/jupyter/labextensions/jupyterannotate/build_log.json
jupyterannotate-0.1.3.data/data/share/jupyter/labextensions/jupyterannotate/install.json
jupyterannotate-0.1.3.data/data/share/jupyter/labextensions/jupyterannotate/package.json
jupyterannotate-0.1.3.data/data/share/jupyter/labextensions/jupyterannotate/static/lib_index_js.9a0214f7bdb2b187ec6b.js
jupyterannotate-0.1.3.dist-info/LICENSE.txt
jupyterannotate-0.1.3.dist-info/METADATA
jupyterannotate-0.1.3.dist-info/WHEEL
jupyterannotate-0.1.3.dist-info/top_level.txt
jupyterannotate-0.1.3.dist-info/RECORD
